aoflagger.cpython-37m-x86_64-linux-gnu.so
aoflagger-3.4.dist-info/METADATA
aoflagger-3.4.dist-info/WHEEL
aoflagger-3.4.dist-info/top_level.txt
aoflagger-3.4.dist-info/COPYING
aoflagger-3.4.dist-info/RECORD
aoflagger.libs/libfftw3f-4367ce36.so.3.3.2
aoflagger.libs/libcasa_scimath_f-3ba21591.so.7
aoflagger.libs/libfftw3_threads-1d56c0c3.so.3.3.2
aoflagger.libs/libcasa_ms-ebf8b3c9.so.7
aoflagger.libs/libcasa_scimath-bcaf3a1f.so.7
aoflagger.libs/libhdf5-78e748b2.so.200.2.0
aoflagger.libs/libblas-357956a1.so.3.4.2
aoflagger.libs/libcasa_casa-aa1f7f3c.so.7
aoflagger.libs/libgslcblas-9055a056.so.0.0.0
aoflagger.libs/libcfitsio-16f89096.so.2.3.37
aoflagger.libs/libgfortran-040039e1.so.5.0.0
aoflagger.libs/libgfortran-91cc3cb1.so.3.0.0
aoflagger.libs/libncurses-a6f90868.so.5.9
aoflagger.libs/libgsl-cb3064f9.so.0.16.0
aoflagger.libs/libtinfo-10270e32.so.5.9
aoflagger.libs/libfftw3f_threads-de15b4b8.so.3.3.2
aoflagger.libs/liblua-f8a31420.so.5.3.6
aoflagger.libs/libhdf5_cpp-64c9359d.so.200.2.0
aoflagger.libs/libreadline-2c5f7b8d.so.6.2
aoflagger.libs/libfftw3-17cc48a2.so.3.3.2
aoflagger.libs/libboost_system-0806f462.so.1.75.0
aoflagger.libs/libsatlas-7e2f78d2.so.3.10
aoflagger.libs/libquadmath-96973f99.so.0.0.0
aoflagger.libs/libaoflagger-de43f15c.so.0
aoflagger.libs/libcasa_measures-3aaf8b1f.so.7
aoflagger.libs/libcasa_tables-1c401830.so.7
aoflagger.libs/libboost_date_time-82d4d183.so.1.75.0
aoflagger.libs/liblapack-1ad85175.so.3.4.2
aoflagger.libs/libpng15-ce838cd1.so.15.13.0
aoflagger.libs/aoflagger/strategies/apertif-2020-05-19.lua
aoflagger.libs/aoflagger/strategies/atca-l-band.lua
aoflagger.libs/aoflagger/strategies/bighorns-default.lua
aoflagger.libs/aoflagger/strategies/wsrt-default.lua
aoflagger.libs/aoflagger/strategies/apertif-default.lua
aoflagger.libs/aoflagger/strategies/jvla-default.lua
aoflagger.libs/aoflagger/strategies/generic-minimal.lua
aoflagger.libs/aoflagger/strategies/apertif-2020-02-26-with-autocorrelations.lua
aoflagger.libs/aoflagger/strategies/nenufar-default.lua
aoflagger.libs/aoflagger/strategies/aartfaac-default.lua
